revidx/__init__.py
revidx/cli.py
revidx/core.py
revidx/utils.py
revidx-1.4.1.dist-info/licenses/LICENSE
revidx-1.4.1.dist-info/METADATA
revidx-1.4.1.dist-info/WHEEL
revidx-1.4.1.dist-info/entry_points.txt
revidx-1.4.1.dist-info/top_level.txt
revidx-1.4.1.dist-info/RECORD
