Metadata-Version: 2.4
Name: revidx
Version: 1.4.1
Summary: reVidx: Re-encode video to AVC/MP3 for legacy compatibility.
Author: voidsnax
License: MIT
Project-URL: Homepage, https://github.com/voidsnax/reVidx
Keywords: video,ffmpeg,converter,h264,mp3
Classifier: Programming Language :: Python :: 3
Classifier: Operating System :: OS Independent
Requires-Python: >=3.7
License-File: LICENSE
Requires-Dist: colorama
Dynamic: license-file
